video2json/__init__.py
video2json/main.py
video2json-0.0.1.dist-info/METADATA
video2json-0.0.1.dist-info/WHEEL
video2json-0.0.1.dist-info/licenses/LICENSE
video2json-0.0.1.dist-info/RECORD
